src/__init__.py
src/__main__.py
src/server.py
src/tools/__init__.py
src/tools/cancel_action.py
src/tools/get_topic_info.py
src/tools/list_actions.py
src/tools/list_services.py
src/tools/list_topics.py
src/tools/publish_action.py
src/tools/publish_service.py
src/tools/publish_topic.py
takanarishimbo_rosbridge_mcp_server-0.3.2.dist-info/METADATA
takanarishimbo_rosbridge_mcp_server-0.3.2.dist-info/WHEEL
takanarishimbo_rosbridge_mcp_server-0.3.2.dist-info/entry_points.txt
takanarishimbo_rosbridge_mcp_server-0.3.2.dist-info/RECORD
