Metadata-Version: 2.4
Name: takanarishimbo-rosbridge-mcp-server
Version: 0.3.2
Summary: A MCP server that provides ROS topic publishing functionality via rosbridge
Project-URL: Homepage, https://github.com/TakanariShimbo/rosbridge-mcp-server
Project-URL: Repository, https://github.com/TakanariShimbo/rosbridge-mcp-server.git
Project-URL: Issues, https://github.com/TakanariShimbo/rosbridge-mcp-server/issues
Author-email: Takanari Shimbo <takanari.shimbo@gmail.com>
License: MIT
Keywords: mcp,robotics,ros,rosbridge,server
Classifier: Development Status :: 4 - Beta
Classifier: Intended Audience :: Developers
Classifier: License :: OSI Approved :: MIT License
Classifier: Programming Language :: Python :: 3
Classifier: Programming Language :: Python :: 3.10
Classifier: Programming Language :: Python :: 3.11
Classifier: Programming Language :: Python :: 3.12
Classifier: Topic :: Software Development :: Libraries
Requires-Python: >=3.10
Requires-Dist: mcp>=1.1.0
Requires-Dist: roslibpy>=1.5.0
